MANIFEST.in
README.txt
setup.cfg
setup.py
cogbin/__init__.py
cogbin/websetup.py
cogbin.egg-info/PKG-INFO
cogbin.egg-info/SOURCES.txt
cogbin.egg-info/dependency_links.txt
cogbin.egg-info/entry_points.txt
cogbin.egg-info/paster_plugins.txt
cogbin.egg-info/requires.txt
cogbin.egg-info/top_level.txt
cogbin/config/__init__.py
cogbin/config/app_cfg.py
cogbin/config/environment.py
cogbin/config/middleware.py
cogbin/controllers/__init__.py
cogbin/controllers/error.py
cogbin/controllers/pypiload.py
cogbin/controllers/pypisync.py
cogbin/controllers/root.py
cogbin/controllers/secure.py
cogbin/controllers/template.py
cogbin/i18n/ru/LC_MESSAGES/cogbin.po
cogbin/lib/__init__.py
cogbin/lib/app_globals.py
cogbin/lib/base.py
cogbin/lib/helpers.py
cogbin/model/__init__.py
cogbin/model/auth.py
cogbin/model/pypi.py
cogbin/public/favicon.ico
cogbin/public/css/style.css
cogbin/public/images/contentbg.png
cogbin/public/images/error.png
cogbin/public/images/header_inner2.png
cogbin/public/images/headerbg.png
cogbin/public/images/info.png
cogbin/public/images/inputbg.png
cogbin/public/images/loginbg.png
cogbin/public/images/loginbottombg.png
cogbin/public/images/loginheader-left.png
cogbin/public/images/loginheader-right.png
cogbin/public/images/menu-item-actibg-first.png
cogbin/public/images/menu-item-actibg.png
cogbin/public/images/menu-item-border.png
cogbin/public/images/menubg.png
cogbin/public/images/ok.png
cogbin/public/images/pagebg.png
cogbin/public/images/star.png
cogbin/public/images/strype2.png
cogbin/public/images/under_the_hood_blue.png
cogbin/templates/__init__.py
cogbin/templates/__init__.pyc
cogbin/templates/about.html
cogbin/templates/authentication.html
cogbin/templates/debug.html
cogbin/templates/error.html
cogbin/templates/footer.html
cogbin/templates/header.html
cogbin/templates/index.html
cogbin/templates/index_org.html
cogbin/templates/login.html
cogbin/templates/master.html
cogbin/templates/sidebars.html
cogbin/tests/__init__.py
cogbin/tests/test_models.py
cogbin/tests/functional/__init__.py
cogbin/tests/functional/test_root.py