Metadata-Version: 1.0
Name: cogbin
Version: 0.2.11dev
Summary: Cogbin is a webtool that sync with pypi, it retrives metadata from it and displays the categories you set up in its web interface. It is running for turbogears2 with turbogears2 categories by default but these can be adjusted at any time. Install it, modify the categories, deploy and you have a list of packages for your software community.
Home-page: https://launchpad.net/cogbin/+download
Author: Lukasz Szybalski
Author-email: szybalski@gmail.com
License: UNKNOWN
Keywords: turbogears2.application
Platform: UNKNOWN
